LICENSE
README.md
setup.py
geopi/__init__.py
geopi/example.py
geopi/geopi.py
geopi.egg-info/PKG-INFO
geopi.egg-info/SOURCES.txt
geopi.egg-info/dependency_links.txt
geopi.egg-info/requires.txt
geopi.egg-info/top_level.txt
geopi/data/city_dict.json
geopi/data/city_shp/china_poi.zip