Metadata-Version: 2.1
Name: geopi
Version: 0.1.7
Summary: A small example package
Home-page: https://github.com/pypa/sampleproject
Author: author
Author-email: author@example.com
Classifier: Programming Language :: Python :: 3
Classifier: License :: OSI Approved :: MIT License
Classifier: Operating System :: OS Independent
Requires-Python: >=3.6
License-File: LICENSE
Requires-Dist: geopandas
Requires-Dist: geopy
Requires-Dist: folium
Requires-Dist: coord-convert
